[
  {
    "author": {
      "id": "tomas@gmail.com",
      "name": "pepe",
      "lastName": "Messi",
      "age": "35",
      "alias": "leo",
      "Avatar": "nada"
    },
    "text": "hola amigos que onda",
    "date": "11/10/2022 18:46:36",
    "id": 1
  },
  {
    "author": {
      "id": "toto@hotmail.com",
      "name": "Tomi",
      "lastName": "Torres",
      "age": "21",
      "alias": "Toto",
      "avatar": "naadaa"
    },
    "text": "Hola, tanto tiempo !!",
    "date": "17/10/2022 17:53:27",
    "id": 2
  },
  {
    "author": {
      "id": "rupert@gmail.com",
      "name": "Rupert",
      "lastName": "Pert",
      "age": "79",
      "alias": "sdfsdf",
      "avatar": "asdsdf"
    },
    "text": "hola como va!",
    "date": "17/10/2022 23:49:53",
    "id": "4d1562a5-e8f6-4207-b3c5-612f39009548"
  }
]